llmflowstack/__init__.py
llmflowstack/callbacks/__init__.py
llmflowstack/callbacks/log_collector.py
llmflowstack/callbacks/stop_on_token.py
llmflowstack/decoders/BaseDecoder.py
llmflowstack/decoders/GPT_OSS.py
llmflowstack/decoders/Gemma.py
llmflowstack/decoders/LLaMA3.py
llmflowstack/decoders/LLaMA4.py
llmflowstack/decoders/MedGemma.py
llmflowstack/decoders/__init__.py
llmflowstack/rag/VectorDatabase.py
llmflowstack/rag/__init__.py
llmflowstack/schemas/__init__.py
llmflowstack/schemas/params.py
llmflowstack/utils/__init__.py
llmflowstack/utils/evaluation_methods.py
llmflowstack/utils/exceptions.py
llmflowstack/utils/generation_utils.py
llmflowstack/utils/logging.py
llmflowstack-1.2.5.dist-info/METADATA
llmflowstack-1.2.5.dist-info/WHEEL
llmflowstack-1.2.5.dist-info/licenses/LICENSE
llmflowstack-1.2.5.dist-info/RECORD
