Metadata-Version: 2.4
Name: llmflowstack
Version: 1.2.5
Summary: LLMFlowStack is a framework for training and using LLMs (LLaMA, GPT-OSS, Gemma, ...). Supports DAPT, fine-tuning, and distributed inference. Public fork without institution-specific components.
Author-email: Gustavo Henrique Ferreira Cruz <gustavohferreiracruz@gmail.com>
License: MIT
License-File: LICENSE
Requires-Python: >=3.12
Requires-Dist: accelerate
Requires-Dist: bert-score
Requires-Dist: bitsandbytes
Requires-Dist: chromadb
Requires-Dist: datasets
Requires-Dist: evaluate
Requires-Dist: huggingface-hub
Requires-Dist: kernels
Requires-Dist: langchain-chroma
Requires-Dist: langchain-community
Requires-Dist: nltk
Requires-Dist: numpy
Requires-Dist: openai-harmony
Requires-Dist: pandas
Requires-Dist: peft
Requires-Dist: rouge-score
Requires-Dist: safetensors
Requires-Dist: scikit-learn
Requires-Dist: scipy
Requires-Dist: sentence-transformers
Requires-Dist: torch
Requires-Dist: torchvision
Requires-Dist: tqdm
Requires-Dist: transformers
Requires-Dist: triton
Requires-Dist: trl
